lks_idprovider_keycloak/__init__.py
lks_idprovider_keycloak/client_credentials_provider.py
lks_idprovider_keycloak/config.py
lks_idprovider_keycloak/provider.py
lks_idprovider_keycloak/rest/__init__.py
lks_idprovider_keycloak/rest/keycloak_oidc_client.py
lks_idprovider_keycloak/utils.py
lks_idprovider_keycloak-0.1.2.dist-info/METADATA
lks_idprovider_keycloak-0.1.2.dist-info/WHEEL
lks_idprovider_keycloak-0.1.2.dist-info/RECORD
