Metadata-Version: 2.3
Name: lks-idprovider-keycloak
Version: 0.1.2
Summary: Keycloak provider implementation for LKS Identity Provider library with FastAPI integration
Author: Raul Medeiros
Author-email: rmedeiros@lksnext.com
Requires-Python: >=3.11
Classifier: Programming Language :: Python :: 3
Classifier: Programming Language :: Python :: 3.11
Classifier: Programming Language :: Python :: 3.12
Classifier: Programming Language :: Python :: 3.13
Requires-Dist: httpx (>=0.28.1,<0.29.0)
Requires-Dist: lks-idprovider-api (>=0.1.3,<0.2.0)
Requires-Dist: python-multipart (>=0.0.9,<0.1.0)
Project-URL: Documentation, https://lks-idprovider.readthedocs.io
Project-URL: Homepage, https://github.com/lks-team/lks-idprovider-python
Project-URL: Issues, https://github.com/lks-team/lks-idprovider-python/issues
Project-URL: Repository, https://github.com/lks-team/lks-idprovider-python
